facemap/.gitignore
facemap/__init__.py
facemap/__main__.py
facemap/keypoints.py
facemap/mouse.png
facemap/ops_user.npy
facemap/process.py
facemap/pupil.py
facemap/roi.py
facemap/running.py
facemap/utils.py
facemap/version.py
facemap/gui/cluster.py
facemap/gui/gui.py
facemap/gui/guiparts.py
facemap/gui/help_windows.py
facemap/gui/io.py
facemap/gui/menus.py
facemap/gui/neural_activity_window.py
facemap/neural_prediction/keypoints_utils.py
facemap/neural_prediction/neural_activity.py
facemap/neural_prediction/neural_model.py
facemap/neural_prediction/prediction_utils.py
facemap/pose/datasets.py
facemap/pose/facemap_network.py
facemap/pose/model_loader.py
facemap/pose/model_training.py
facemap/pose/pose.py
facemap/pose/pose_gui.py
facemap/pose/pose_helper_functions.py
facemap/pose/refine_pose.py
facemap/pose/transforms.py
facemap-1.0.8.dist-info/licenses/LICENSE
facemap-1.0.8.dist-info/METADATA
facemap-1.0.8.dist-info/WHEEL
facemap-1.0.8.dist-info/entry_points.txt
facemap-1.0.8.dist-info/top_level.txt
facemap-1.0.8.dist-info/RECORD
