Metadata-Version: 2.4
Name: facemap
Version: 1.0.8
Summary: Pose estimation and processing SVDs of videos
Home-page: https://github.com/mouseland/facemap
Author: Carsen Stringer & Atika Syeda
Author-email: carsen.stringer@gmail.com
License: GPLv3
Classifier: Programming Language :: Python :: 3
Classifier: License :: OSI Approved :: GNU General Public License v3 (GPLv3)
Classifier: Operating System :: OS Independent
License-File: LICENSE
Requires-Dist: numpy<2.0,>=1.16
Requires-Dist: scipy
Requires-Dist: natsort
Requires-Dist: tqdm
Requires-Dist: numba>=0.43.1
Requires-Dist: opencv-python-headless<4.10
Requires-Dist: torch>=1.9
Requires-Dist: h5py
Requires-Dist: scikit-learn
Provides-Extra: docs
Requires-Dist: sphinx>=3.0; extra == "docs"
Requires-Dist: sphinxcontrib-apidoc; extra == "docs"
Requires-Dist: sphinx_rtd_theme; extra == "docs"
Provides-Extra: gui
Requires-Dist: pyqtgraph>=0.12.0; extra == "gui"
Requires-Dist: pyqt6; extra == "gui"
Requires-Dist: pyqt6.sip; extra == "gui"
Requires-Dist: qtpy; extra == "gui"
Requires-Dist: matplotlib; extra == "gui"
Dynamic: author
Dynamic: author-email
Dynamic: classifier
Dynamic: description
Dynamic: description-content-type
Dynamic: home-page
Dynamic: license
Dynamic: license-file
Dynamic: provides-extra
Dynamic: requires-dist
Dynamic: summary
